Metadata-Version: 2.1
Name: gpttools
Version: 0.0.1
Summary: GPT-Tools - Easy-to-use Python module with tools for OpenAI GPT-3. Natural language processing, text generation, and conversation simulations included.
Home-page: https://github.com/meyiapir/gpt_tools
Author: meyap
Author-email: mmeyiapir@gmail.com
License: Apache License, Version 2.0, see LICENSE file
License-File: LICENSE.txt
License-File: NOTICE.txt
